Metadata-Version: 2.1
Name: tapyr
Version: 0.2.0
Summary: Python binding for TAPIR
Home-page: https://github.com/tap-ir/tapyr
Author: Solal Jacob
Author-email: tapir42@protonmail.com
License: AGPLv3.0
Platform: UNKNOWN
License-File: LICENSE
